hider/__init__.py
hider/core.py
hider/hp.py
hider/image.py
hider/text.py
hider/util.py
hider-1.1.dist-info/LICENSE
hider-1.1.dist-info/METADATA
hider-1.1.dist-info/WHEEL
hider-1.1.dist-info/top_level.txt
hider-1.1.dist-info/RECORD
