Metadata-Version: 2.1
Name: hider
Version: 1.1
Summary: Image steganography package.
Home-page: https://github.com/cihatceliker/hider
Author: clkr
Author-email: clkrv1@gmail.com
License: UNKNOWN
Project-URL: Bug Tracker, https://github.com/cihatceliker/hider/issues
Platform: UNKNOWN
Classifier: Programming Language :: Python :: 3
Classifier: License :: OSI Approved :: MIT License
Classifier: Operating System :: OS Independent
Requires-Python: >=3.6
